{
  "@context": "https://schema.org",
  "@graph": [
    {
      "@type": "MedicalCondition",
      "@id": "https://www.physioactif.com/en/guide-complet/whiplash#condition",
      "name": "Entorse cervicale (Whiplash)",
      "alternateName": [
        "Whiplash",
        "coup du lapin",
        "entorse cervicale",
        "cervical sprain",
        "whiplash injury",
        "whiplash-associated disorders (WAD)"
      ],
      "description": "Condition médicale affectant le système musculosquelettique nécessitant une prise en charge en physiothérapie.",
      "sameAs": [
        "https://fr.wikipedia.org/wiki/Coup_du_lapin",
        "https://en.wikipedia.org/wiki/Whiplash_(medicine)",
        "https://www.wikidata.org/wiki/Q329638",
        "https://meshb.nlm.nih.gov/record/ui?ui=D014911",
        "http://snomed.info/id/242816008"
      ],
      "code": [
        {
          "@type": "MedicalCode",
          "code": "S13.4",
          "codingSystem": "ICD-10"
        },
        {
          "@type": "MedicalCode",
          "code": "ND14.10",
          "codingSystem": "ICD-11"
        }
      ]
    },
    {
      "@type": "MedicalWebPage",
      "@id": "https://www.physioactif.com/en/guide-complet/whiplash#article",
      "author": {
        "@type": "Person",
        "@id": "https://www.physioactif.com/en/equipe/ariel-desjardins-charbonneau/#person"
      },
      "datePublished": "2025-09-26",
      "name": "Whiplash - Guide Complet",
      "headline": "Whiplash: Symptômes, Causes, Diagnostic et Traitement en Physiothérapie",
      "about": [
        {
          "@id": "https://www.physioactif.com/en/guide-complet/whiplash#condition"
        },
        {
          "@type": "MedicalTherapy",
          "name": "Physiothérapie",
          "alternateName": [
            "Physical therapy",
            "Kinésithérapie",
            "Fisioterapia"
          ],
          "sameAs": [
            "https://www.physioactif.com/en/guide-complet/physiotherapie",
            "https://www.wikidata.org/wiki/Q186005",
            "https://en.wikipedia.org/wiki/Physical_therapy",
            "https://fr.wikipedia.org/wiki/Kinésithérapie",
            "https://meshb.nlm.nih.gov/record/ui?ui=D026761",
            "https://www.merriam-webster.com/dictionary/physiotherapy",
            "https://www.britannica.com/topic/physical-therapy"
          ]
        }
      ],
      "mainEntity": {
        "@id": "https://www.physioactif.com/en/guide-complet/whiplash#condition"
      },
      "speakable": {
        "@type": "SpeakableSpecification",
        "cssSelector": [
          ".header_heading",
          ".header_content .text-style-muted.w-richtext",
          ".section_article .text-rich-text h2"
        ]
      },
      "specialty": [
        "Physiotherapy",
        "Musculoskeletal",
        "SportsMedicine"
      ],
      "medicalAudience": [
        {
          "@type": "Patient"
        },
        {
          "@type": "MedicalAudience",
          "audienceType": "General Public"
        }
      ],
      "reviewedBy": {
        "@id": "https://www.physioactif.com/en/#org"
      },
      "provider": {
        "@id": "https://www.physioactif.com/en/#org"
      },
      "inLanguage": [
        "en-CA"
      ],
      "isPartOf": {
        "@id": "https://www.physioactif.com/en/#website"
      },
      "mentions": [
        {
          "@type": "MedicalTherapy",
          "name": "Physiothérapie",
          "alternateName": [
            "Physical therapy",
            "Kinésithérapie",
            "Fisioterapia"
          ],
          "sameAs": [
            "https://www.physioactif.com/en/guide-complet/physiotherapie",
            "https://www.wikidata.org/wiki/Q186005",
            "https://en.wikipedia.org/wiki/Physical_therapy",
            "https://fr.wikipedia.org/wiki/Kinésithérapie",
            "https://meshb.nlm.nih.gov/record/ui?ui=D026761",
            "https://www.merriam-webster.com/dictionary/physiotherapy",
            "https://www.britannica.com/topic/physical-therapy"
          ]
        },
        {
          "@type": "DefinedTerm",
          "name": "Entorse cervicale (Whiplash)",
          "description": "Étirement ou déchirure des ligaments du cou",
          "sameAs": [
            "https://fr.wikipedia.org/wiki/Coup_du_lapin",
            "https://en.wikipedia.org/wiki/Whiplash_(medicine)",
            "https://www.wikidata.org/wiki/Q329638",
            "https://meshb.nlm.nih.gov/record/ui?ui=D014911"
          ]
        },
        {
          "@type": "DefinedTerm",
          "name": "Cervicalgie",
          "description": "Douleur au niveau de la région cervicale du cou",
          "sameAs": [
            "https://fr.wikipedia.org/wiki/Cervicalgie",
            "https://en.wikipedia.org/wiki/Neck_pain",
            "https://www.wikidata.org/wiki/Q1758730",
            "https://meshb.nlm.nih.gov/record/ui?ui=D019547"
          ]
        }
      ]
    },
    {
      "@type": "WebPage",
      "@id": "https://www.physioactif.com/en/guide-complet/whiplash#webpage",
      "datePublished": "2025-09-26",
      "url": "https://www.physioactif.com/en/guide-complet/whiplash",
      "name": "Whiplash - Guide Complet | Physioactif",
      "description": "Guide complet sur whiplash: causes, symptômes, diagnostic et traitements en physiothérapie par les experts de Physioactif.",
      "mainEntity": {
        "@id": "https://www.physioactif.com/en/guide-complet/whiplash#condition"
      },
      "about": {
        "@id": "https://www.physioactif.com/en/guide-complet/whiplash#condition"
      },
      "breadcrumb": {
        "@type": "BreadcrumbList",
        "@id": "https://www.physioactif.com/en/guide-complet/whiplash#breadcrumb",
        "itemListElement": [
          {
            "@type": "ListItem",
            "position": 1,
            "name": "Accueil",
            "item": "https://www.physioactif.com/en/"
          },
          {
            "@type": "ListItem",
            "position": 2,
            "name": "Guide Complet",
            "item": "https://www.physioactif.com/en/guide-complet"
          },
          {
            "@type": "ListItem",
            "position": 3,
            "name": "Whiplash",
            "item": "https://www.physioactif.com/en/guide-complet/whiplash"
          }
        ]
      },
      "isPartOf": {
        "@id": "https://www.physioactif.com/en/#website"
      },
      "inLanguage": [
        "en-CA"
      ],
      "potentialAction": {
        "@type": "ReadAction",
        "target": {
          "@type": "EntryPoint",
          "urlTemplate": "https://www.physioactif.com/en/guide-complet/whiplash",
          "actionPlatform": [
            "http://schema.org/DesktopWebPlatform",
            "http://schema.org/MobileWebPlatform"
          ]
        }
      },
      "relatedLink": [
        "https://physioactif.clinicmaster.com/clinic-selection?lang=fr-CA"
      ],
      "publisher": {
        "@id": "https://www.physioactif.com/en/#org"
      }
    }
  ]
}