{
  "@context": "https://schema.org",
  "@type": "MedicalWebPage",
  "@id": "https://www.physioactif.com/diagnostic-et-traitement/pathologies/vertiges-et-etourdissements/#webpage",
  "author": {
    "@type": "Person",
    "@id": "https://www.physioactif.com/equipe/alexis-gougeon/#person"
  },
  "speakable": {
    "@type": "SpeakableSpecification",
    "cssSelector": [
      ".header_heading",
      ".header_content .max-width-medium",
      ".perks_content-right h2",
      ".perks_content-right .w-richtext"
    ]
  },
  "datePublished": "2025-09-26",
  "url": "https://www.physioactif.com/diagnostic-et-traitement/pathologies/vertiges-et-etourdissements/",
  "name": "Retrouvez votre équilibre et votre stabilité naturelle",
  "description": "Retrouvez votre équilibre et votre stabilité naturelle",
  "inLanguage": [
    "fr-CA"
  ],
  "isPartOf": {
    "@id": "https://www.physioactif.com/#website"
  },
  "about": [
    {
      "@type": "DefinedTerm",
      "name": "Vertige",
      "description": "Sensation de rotation ou mouvement de l'environnement",
      "sameAs": [
        "https://fr.wikipedia.org/wiki/Vertige",
        "https://en.wikipedia.org/wiki/Vertigo",
        "https://www.wikidata.org/wiki/Q193216",
        "https://meshb.nlm.nih.gov/record/ui?ui=D014717",
        "https://www.merriam-webster.com/medical/vertigo"
      ]
    },
    {
      "@type": "MedicalTherapy",
      "name": "Physiothérapie",
      "alternateName": [
        "Physical therapy",
        "Kinésithérapie",
        "Fisioterapia"
      ],
      "sameAs": [
        "https://www.physioactif.com/guide-complet/physiotherapie",
        "https://www.wikidata.org/wiki/Q186005",
        "https://en.wikipedia.org/wiki/Physical_therapy",
        "https://fr.wikipedia.org/wiki/Kinésithérapie",
        "https://meshb.nlm.nih.gov/record/ui?ui=D026761",
        "https://www.merriam-webster.com/dictionary/physiotherapy",
        "https://www.britannica.com/topic/physical-therapy"
      ]
    }
  ],
  "specialty": "Physiotherapy",
  "provider": {
    "@id": "https://www.physioactif.com/#org"
  },
  "potentialAction": {
    "@type": "ReserveAction",
    "target": {
      "@type": "EntryPoint",
      "urlTemplate": "https://physioactif.clinicmaster.com/clinic-selection?lang=fr-CA",
      "inLanguage": [
        "fr-CA"
      ]
    },
    "result": {
      "@type": "Reservation",
      "name": "Prendre rendez-vous"
    }
  },
  "breadcrumb": {
    "@type": "BreadcrumbList",
    "itemListElement": [
      {
        "@type": "ListItem",
        "position": 1,
        "name": "Accueil",
        "item": "https://www.physioactif.com/"
      },
      {
        "@type": "ListItem",
        "position": 2,
        "name": "Diagnostic et traitement",
        "item": "https://www.physioactif.com/diagnostic-et-traitement/"
      },
      {
        "@type": "ListItem",
        "position": 3,
        "name": "Pathologies",
        "item": "https://www.physioactif.com/diagnostic-et-traitement/pathologies/"
      },
      {
        "@type": "ListItem",
        "position": 4,
        "name": "Vertiges Et Etourdissements",
        "item": "https://www.physioactif.com/diagnostic-et-traitement/pathologies/vertiges-et-etourdissements/"
      }
    ]
  },
  "mentions": [
    {
      "@id": "https://www.physioactif.com/services/accident-de-la-route-saaq/#therapy"
    },
    {
      "@id": "https://www.physioactif.com/services/ancien-combattant/#therapy"
    },
    {
      "@id": "https://www.physioactif.com/services/deuxieme-avis-sur-diagnostic-et-traitement/#therapy"
    },
    {
      "@id": "https://www.physioactif.com/services/physiotherapie-sportive/#therapy"
    },
    {
      "@id": "https://www.physioactif.com/services/reeducation-vestibulaire-pour-vertiges-et-etourdissements/#therapy"
    }
  ]
}